{
  "all": [ "central", "east", "west", "corp-monitoring" ],

  "corp-monitoring": [ "corp-monitoring-cluster-101" ],

  "central": [ "central-tx-austin", "central-mo-kc" ],
    "central-tx-austin": [ "central-tx-austin-101", "central-tx-austin-102" ],
    "central-mo-kc": [ "central-mo-kc-101", "central-mo-kc-102" ],

  "east": [ "east-ga-atlanta", "east-nc-raleigh" ],
    "east-ga-atlanta": [ "east-ga-atlanta-101", "east-ga-atlanta-102" ],
    "east-nc-raleigh": [ "east-nc-raleigh-101", "east-nc-raleigh-102" ],

  "west": [ "west-ca-sd", "west-wa-seattle", "west-wa-redmond" ],
    "west-ca-sd": [ "west-ca-sd-101", "west-ca-sd-102" ],
    "west-wa-seattle": [ "west-wa-seattle-101", "west-wa-seattle-102" ],
    "west-wa-redmond": [ "west-wa-redmond-101", "west-wa-redmond-102" ]
}
